{"namedChunkGroups":{"polyfill":{"name":"polyfill","assets":[{"name":"webpack-runtime-e602ef02804f24c5086c.js","size":3792},{"name":"polyfill-0c275ed069d54a78a898.js","size":82633}],"filteredAssets":0,"assetsSize":86425,"filteredAuxiliaryAssets":2,"auxiliaryAssetsSize":216912},"app":{"name":"app","assets":[{"name":"webpack-runtime-e602ef02804f24c5086c.js","size":3792},{"name":"framework-45c977225e94bf4f76d8.js","size":129827},{"name":"app-6820781bf424cfcb8a34.js","size":74106}],"filteredAssets":0,"assetsSize":207725,"filteredAuxiliaryAssets":3,"auxiliaryAssetsSize":666029},"component---src-pages-404-js":{"name":"component---src-pages-404-js","assets":[{"name":"component---src-pages-404-js-c37139e5806ec4c31dc2.js","size":808}],"filteredAssets":0,"assetsSize":808,"filteredAuxiliaryAssets":1,"auxiliaryAssetsSize":1883},"component---src-pages-index-js":{"name":"component---src-pages-index-js","assets":[{"name":"component---src-pages-index-js-9146632f05d8eb4cd9e4.js","size":4562}],"filteredAssets":0,"assetsSize":4562,"filteredAuxiliaryAssets":1,"auxiliaryAssetsSize":7575}},"assetsByChunkName":{"polyfill":["webpack-runtime-e602ef02804f24c5086c.js","polyfill-0c275ed069d54a78a898.js"],"app":["webpack-runtime-e602ef02804f24c5086c.js","framework-45c977225e94bf4f76d8.js","app-6820781bf424cfcb8a34.js"],"component---src-pages-404-js":["component---src-pages-404-js-c37139e5806ec4c31dc2.js"],"component---src-pages-index-js":["component---src-pages-index-js-9146632f05d8eb4cd9e4.js"]},"childAssetsByChunkName":{}}